himile_log.py
himile_log-0.1.0.dist-info/METADATA
himile_log-0.1.0.dist-info/WHEEL
himile_log-0.1.0.dist-info/top_level.txt
himile_log-0.1.0.dist-info/RECORD
