Metadata-Version: 2.1
Name: himile-log
Version: 0.1.0
Summary: the log Create By Yi Sun
Author: Zongwei Du
Author-email: pxwtp6519@gmail.com
Classifier: Programming Language :: Python :: 3
Classifier: License :: OSI Approved :: MIT License
Classifier: Operating System :: OS Independent
Requires-Python: >=3.6
Requires-Dist: loguru
